credmodex/__init__.py
credmodex/config.py
credmodex/credlab.py
credmodex/discriminancy/__init__.py
credmodex/discriminancy/correlation/__init__.py
credmodex/discriminancy/correlation/correlation.py
credmodex/discriminancy/discriminants/__init__.py
credmodex/discriminancy/discriminants/gini_discriminant.py
credmodex/discriminancy/discriminants/iv_discriminant.py
credmodex/discriminancy/discriminants/ks_discriminant.py
credmodex/discriminancy/discriminants/psi_discriminant.py
credmodex/discriminancy/goodness_of_fit/__init__.py
credmodex/discriminancy/goodness_of_fit/goodness_of_fit.py
credmodex/models/__init__.py
credmodex/models/base_model.py
credmodex/models/non_parametric_models/__init__.py
credmodex/models/non_parametric_models/ada_boost.py
credmodex/models/non_parametric_models/bagging.py
credmodex/models/non_parametric_models/decision_tree.py
credmodex/models/non_parametric_models/extra_tree.py
credmodex/models/non_parametric_models/gradient_boost.py
credmodex/models/non_parametric_models/hist_gradient_boost.py
credmodex/models/non_parametric_models/k_neighbors.py
credmodex/models/non_parametric_models/multi_layer_perceptrons.py
credmodex/models/non_parametric_models/nusvm.py
credmodex/models/non_parametric_models/random_forest.py
credmodex/models/non_parametric_models/stacking.py
credmodex/models/non_parametric_models/svm.py
credmodex/models/non_parametric_models/voting.py
credmodex/models/non_parametric_models/xgboost.py
credmodex/models/parametric_models/__init__.py
credmodex/models/parametric_models/logistic.py
credmodex/models/parametric_models/modified_huber.py
credmodex/models/parametric_models/probit.py
credmodex/models/probability_models/__init__.py
credmodex/models/probability_models/bernoulli_naive_bayes.py
credmodex/models/probability_models/gaussian_naive_bayes.py
credmodex/models/probability_models/multinomial_naive_bayes.py
credmodex/models/treatment/__init__.py
credmodex/models/treatment/treatment_func.py
credmodex/pricing/__init__.py
credmodex-0.2.8.dist-info/licenses/LICENSE
credmodex-0.2.8.dist-info/METADATA
credmodex-0.2.8.dist-info/WHEEL
credmodex-0.2.8.dist-info/top_level.txt
credmodex-0.2.8.dist-info/RECORD
