Metadata-Version: 2.4
Name: credmodex
Version: 0.2.8
Summary: A Python library for credit risk modeling
Author-email: Gustavo Meira Filho <gustavojvmf@gmail.com>
License-Expression: MIT
Project-URL: Source, https://github.com/Gumodex/cred-modex
Requires-Python: >=3.8
License-File: LICENSE
Requires-Dist: numpy>=2.0
Requires-Dist: pandas>=2.0
Requires-Dist: scikit-learn>=1.6
Requires-Dist: matplotlib>=3.10
Requires-Dist: plotly>=6.0
Requires-Dist: scipy>=1.15
Requires-Dist: optbinning>=0.20
Requires-Dist: statsmodels>=0.14
Requires-Dist: xgboost>=3.0
Dynamic: license-file
